res_return.py
pypi_mcp-0.1.0.dist-info/METADATA
pypi_mcp-0.1.0.dist-info/WHEEL
pypi_mcp-0.1.0.dist-info/top_level.txt
pypi_mcp-0.1.0.dist-info/RECORD
